pywaiwera/__init__.py
pywaiwera/common.py
pywaiwera/docker.py
pywaiwera-1.5.1.dist-info/METADATA
pywaiwera-1.5.1.dist-info/WHEEL
pywaiwera-1.5.1.dist-info/entry_points.txt
pywaiwera-1.5.1.dist-info/top_level.txt
pywaiwera-1.5.1.dist-info/RECORD
