Metadata-Version: 2.4
Name: pywaiwera
Version: 1.5.1
Summary: Python package for the Waiwera simulator
Author-email: Waiwera Project <waiwera.project@gmail.com>
Project-URL: repository, https://github.com/waiwera/waiwera
Classifier: Programming Language :: Python :: 2
Classifier: Programming Language :: Python :: 3
Classifier: License :: OSI Approved :: GNU Lesser General Public License v3 (LGPLv3)
Classifier: Operating System :: OS Independent
Requires-Python: >=2.7
